scrapy_arweave/__init__.py
scrapy_arweave/client.py
scrapy_arweave/feedexport.py
scrapy_arweave/pipelines.py
scrapy_arweave-0.1.0.dist-info/LICENSE.txt
scrapy_arweave-0.1.0.dist-info/METADATA
scrapy_arweave-0.1.0.dist-info/WHEEL
scrapy_arweave-0.1.0.dist-info/top_level.txt
scrapy_arweave-0.1.0.dist-info/RECORD
