Metadata-Version: 2.1
Name: scrapy-arweave
Version: 0.1.0
Summary: Scrapy is a popular open-source and collaborative python framework for extracting the data you need from websites. scrapy-arweave provides scrapy pipelines and feed exports to store items into Arweave.
Home-page: https://github.com/pawanpaudel93/scrapy-arweave
Author: Pawan Paudel
Author-email: pawanpaudel93@gmail.com
License: ISC
Classifier: License :: OSI Approved :: MIT License
Classifier: Development Status :: 3 - Alpha
Classifier: Programming Language :: Python :: 3
Classifier: Programming Language :: Python :: 3.6
Classifier: Programming Language :: Python :: 3.7
Classifier: Programming Language :: Python :: 3.8
Classifier: Programming Language :: Python :: 3.9
Classifier: Programming Language :: Python :: 3.10
Classifier: Operating System :: OS Independent
Requires-Python: >=3.0
License-File: LICENSE.txt
Requires-Dist: python-magic
Requires-Dist: pyarweave
